pybald/__init__.py
pybald/default.py
pybald/test.py
pybald/watch.py
pybald/config/__init__.py
pybald/config/constants.py
pybald/core/__init__.py
pybald/core/controllers.py
pybald/core/forms.py
pybald/core/helpers.py
pybald/core/logs.py
pybald/core/models.py
pybald/core/page.py
pybald/core/router.py
pybald/core/templates.py
pybald/core/default_templates/stack_trace.html.template
pybald/core/default_templates/forms/fieldset.form.template
pybald/core/default_templates/forms/grid.form.template
pybald/core/django/__init__.py
pybald/core/django/paginator.py
pybald/core/middleware/__init__.py
pybald/core/middleware/db_middleware.py
pybald/core/middleware/errors.py
pybald/core/middleware/sessions.py
pybald/core/middleware/users.py
pybald/db/__init__.py
pybald/db/cache.py
pybald/db/db_engine.py
pybald/db/ext.py
pybald/db/instrumented_proxy.py
pybald/db/magic.py
pybald/util/__init__.py
pybald/util/command_line.py
pybald/util/console.py
pybald/util/context.py
pybald/util/dev_server.py
pybald/util/static_serve.py
pybald/util/text.py
tests/__init__.py
tests/functional/__init__.py
tests/functional/test_errors.py
tests/functional/test_static_server.py
tests/functional/test_xss.py
tests/sample_project/__init__.py
tests/sample_project/project.py
tests/sample_project/sample.py
tests/unit/__init__.py
tests/unit/test_console.py
tests/unit/test_forms.py
tests/unit/test_router.py
tests/unit/config/__init__.py
tests/unit/config/test_configuration.py
tests/unit/config/test_constants.py
tests/unit/config/test_engine_config.py
tests/unit/config/test_registries.py
tests/unit/controllers/__init__.py
tests/unit/controllers/test_controllers.py
tests/unit/models/__init__.py
tests/unit/models/test_db_ext.py
tests/unit/models/test_orm.py
tests/unit/templates/__init__.py
tests/unit/templates/test_paginator.py
tests/unit/templates/test_static_asset_helpers.py
tests/unit/templates/test_templates.py
tests/unit/utilities/__init__.py
tests/unit/utilities/test_text.py
pybald-0.5.2.dist-info/LICENSE
pybald-0.5.2.dist-info/METADATA
pybald-0.5.2.dist-info/WHEEL
pybald-0.5.2.dist-info/top_level.txt
pybald-0.5.2.dist-info/RECORD
