Metadata-Version: 2.1
Name: pybald
Version: 0.5.2
Summary: A lightweight python web framework
Home-page: http://pybald.com/
Author: Michael Kowalchik
Author-email: mikepk@tenzerolab.com
License: MIT
Keywords: web framework
Platform: UNKNOWN
Requires-Dist: Mako (==1.0.6)
Requires-Dist: Routes (==2.4.1)
Requires-Dist: SQLAlchemy (==1.1.10)
Requires-Dist: WTForms (==2.1)
Requires-Dist: WebOb (==1.7.2)
Requires-Dist: alembic (==0.9.2)
Requires-Dist: six (==1.10.0)
Provides-Extra: docs
Requires-Dist: Sphinx (>=1.6.2) ; extra == 'docs'
Provides-Extra: tests
Requires-Dist: pytest (>=3.1.1) ; extra == 'tests'
